pymodaq_plugins_crystal_technology/__init__.py
pymodaq_plugins_crystal_technology/utils.py
pymodaq_plugins_crystal_technology/daq_move_plugins/__init__.py
pymodaq_plugins_crystal_technology/daq_move_plugins/daq_move_AOTF.py
pymodaq_plugins_crystal_technology/daq_viewer_plugins/__init__.py
pymodaq_plugins_crystal_technology/daq_viewer_plugins/plugins_0D/__init__.py
pymodaq_plugins_crystal_technology/daq_viewer_plugins/plugins_1D/__init__.py
pymodaq_plugins_crystal_technology/daq_viewer_plugins/plugins_2D/__init__.py
pymodaq_plugins_crystal_technology/daq_viewer_plugins/plugins_ND/__init__.py
pymodaq_plugins_crystal_technology/hardware/__init__.py
pymodaq_plugins_crystal_technology/hardware/aods_controller.py
pymodaq_plugins_crystal_technology/hardware/calibration.toml
pymodaq_plugins_crystal_technology/resources/VERSION
pymodaq_plugins_crystal_technology/resources/__init__.py
pymodaq_plugins_crystal_technology/resources/config_template.toml
pymodaq_plugins_crystal_technology-5.0.1.dist-info/METADATA
pymodaq_plugins_crystal_technology-5.0.1.dist-info/WHEEL
pymodaq_plugins_crystal_technology-5.0.1.dist-info/entry_points.txt
pymodaq_plugins_crystal_technology-5.0.1.dist-info/licenses/LICENSE
pymodaq_plugins_crystal_technology-5.0.1.dist-info/RECORD
